[
  {
    "inputs": [],
    "stateMutability": "nonpayable",
    "type": "constructor"
  },
  {
    "inputs": [],
    "name": "BetMismatch",
    "type": "error"
  },
  {
    "inputs": [],
    "name": "CannotChallengeSelf",
    "type": "error"
  },
  {
    "inputs": [],
    "name": "CannotPlaySelf",
    "type": "error"
  },
  {
    "inputs": [],
    "name": "CellOccupied",
    "type": "error"
  },
  {
    "inputs": [],
    "name": "ChallengeAlreadyAccepted",
    "type": "error"
  },
  {
    "inputs": [],
    "name": "ChallengeNotFound",
    "type": "error"
  },
  {
    "inputs": [],
    "name": "EnforcedPause",
    "type": "error"
  },
  {
    "inputs": [],
    "name": "ExpectedPause",
    "type": "error"
  },
  {
    "inputs": [],
    "name": "GameAlreadyStarted",
    "type": "error"
  },
  {
    "inputs": [],
    "name": "GameNotActive",
    "type": "error"
  },
  {
    "inputs": [],
    "name": "InvalidBetAmount",
    "type": "error"
  },
  {
    "inputs": [],
    "name": "InvalidChallenge",
    "type": "error"
  },
  {
    "inputs": [],
    "name": "InvalidFeePercent",
    "type": "error"
  },
  {
    "inputs": [],
    "name": "InvalidGameId",
    "type": "error"
  },
  {
    "inputs": [],
    "name": "InvalidMove",
    "type": "error"
  },
  {
    "inputs": [],
    "name": "InvalidPlayerAddress",
    "type": "error"
  },
  {
    "inputs": [],
    "name": "InvalidTimeout",
    "type": "error"
  },
  {
    "inputs": [],
    "name": "NotAdmin",
    "type": "error"
  },
  {
    "inputs": [],
    "name": "NotRegistered",
    "type": "error"
  },
  {
    "inputs": [],
    "name": "NotYourTurn",
    "type": "error"
  },
  {
    "inputs": [
      {
        "internalType": "address",
        "name": "owner",
        "type": "address"
      }
    ],
    "name": "OwnableInvalidOwner",
    "type": "error"
  },
  {
    "inputs": [
      {
        "internalType": "address",
        "name": "account",
        "type": "address"
      }
    ],
    "name": "OwnableUnauthorizedAccount",
    "type": "error"
  },
  {
    "inputs": [],
    "name": "PayoutTransferFailed",
    "type": "error"
  },
  {
    "inputs": [],
    "name": "ReentrancyGuardReentrantCall",
    "type": "error"
  },
  {
    "inputs": [],
    "name": "RefundTransferFailed",
    "type": "error"
  },
  {
    "inputs": [],
    "name": "TimeoutNotReached",
    "type": "error"
  },
  {
    "inputs": [],
    "name": "TokenNotSupported",
    "type": "error"
  },
  {
    "inputs": [],
    "name": "UnauthorizedForfeit",
    "type": "error"
  },
  {
    "inputs": [],
    "name": "UsernameInvalid",
    "type": "error"
  },
  {
    "inputs": [],
    "name": "UsernameTaken",
    "type": "error"
  },
  {
    "anonymous": false,
    "inputs": [
      {
        "indexed": true,
        "internalType": "address",
        "name": "admin",
        "type": "address"
      }
    ],
    "name": "AdminAdded",
    "type": "event"
  },
  {
    "anonymous": false,
    "inputs": [
      {
        "indexed": true,
        "internalType": "address",
        "name": "admin",
        "type": "address"
      }
    ],
    "name": "AdminRemoved",
    "type": "event"
  },
  {
    "anonymous": false,
    "inputs": [
      {
        "indexed": true,
        "internalType": "uint256",
        "name": "challengeId",
        "type": "uint256"
      },
      {
        "indexed": true,
        "internalType": "uint256",
        "name": "gameId",
        "type": "uint256"
      }
    ],
    "name": "ChallengeAccepted",
    "type": "event"
  },
  {
    "anonymous": false,
    "inputs": [
      {
        "indexed": true,
        "internalType": "uint256",
        "name": "challengeId",
        "type": "uint256"
      },
      {
        "indexed": true,
        "internalType": "address",
        "name": "challenger",
        "type": "address"
      },
      {
        "indexed": true,
        "internalType": "address",
        "name": "challenged",
        "type": "address"
      },
      {
        "indexed": false,
        "internalType": "uint256",
        "name": "betAmount",
        "type": "uint256"
      }
    ],
    "name": "ChallengeCreated",
    "type": "event"
  },
  {
    "anonymous": false,
    "inputs": [
      {
        "indexed": true,
        "internalType": "uint256",
        "name": "gameId",
        "type": "uint256"
      },
      {
        "indexed": true,
        "internalType": "address",
        "name": "playerOne",
        "type": "address"
      },
      {
        "indexed": false,
        "internalType": "uint256",
        "name": "betAmount",
        "type": "uint256"
      },
      {
        "indexed": false,
        "internalType": "uint8",
        "name": "moveIndex",
        "type": "uint8"
      },
      {
        "indexed": false,
        "internalType": "address",
        "name": "tokenAddress",
        "type": "address"
      }
    ],
    "name": "GameCreated",
    "type": "event"
  },
  {
    "anonymous": false,
    "inputs": [
      {
        "indexed": true,
        "internalType": "uint256",
        "name": "gameId",
        "type": "uint256"
      },
      {
        "indexed": true,
        "internalType": "address",
        "name": "winner",
        "type": "address"
      }
    ],
    "name": "GameForfeited",
    "type": "event"
  },
  {
    "anonymous": false,
    "inputs": [
      {
        "indexed": true,
        "internalType": "uint256",
        "name": "gameId",
        "type": "uint256"
      },
      {
        "indexed": true,
        "internalType": "address",
        "name": "playerTwo",
        "type": "address"
      },
      {
        "indexed": false,
        "internalType": "uint8",
        "name": "moveIndex",
        "type": "uint8"
      }
    ],
    "name": "GameJoined",
    "type": "event"
  },
  {
    "anonymous": false,
    "inputs": [
      {
        "indexed": true,
        "internalType": "uint256",
        "name": "gameId",
        "type": "uint256"
      },
      {
        "indexed": true,
        "internalType": "address",
        "name": "winner",
        "type": "address"
      },
      {
        "indexed": false,
        "internalType": "uint256",
        "name": "payout",
        "type": "uint256"
      }
    ],
    "name": "GameWon",
    "type": "event"
  },
  {
    "anonymous": false,
    "inputs": [
      {
        "indexed": true,
        "internalType": "uint256",
        "name": "gameId",
        "type": "uint256"
      },
      {
        "indexed": true,
        "internalType": "address",
        "name": "winner",
        "type": "address"
      },
      {
        "indexed": false,
        "internalType": "string",
        "name": "winnerUsername",
        "type": "string"
      },
      {
        "indexed": true,
        "internalType": "address",
        "name": "opponent",
        "type": "address"
      },
      {
        "indexed": false,
        "internalType": "string",
        "name": "opponentUsername",
        "type": "string"
      }
    ],
    "name": "LatestWinRecorded",
    "type": "event"
  },
  {
    "anonymous": false,
    "inputs": [
      {
        "indexed": true,
        "internalType": "uint256",
        "name": "gameId",
        "type": "uint256"
      },
      {
        "indexed": true,
        "internalType": "address",
        "name": "player",
        "type": "address"
      },
      {
        "indexed": false,
        "internalType": "uint8",
        "name": "moveIndex",
        "type": "uint8"
      }
    ],
    "name": "MovePlayed",
    "type": "event"
  },
  {
    "anonymous": false,
    "inputs": [
      {
        "indexed": true,
        "internalType": "address",
        "name": "previousOwner",
        "type": "address"
      },
      {
        "indexed": true,
        "internalType": "address",
        "name": "newOwner",
        "type": "address"
      }
    ],
    "name": "OwnershipTransferred",
    "type": "event"
  },
  {
    "anonymous": false,
    "inputs": [
      {
        "indexed": false,
        "internalType": "address",
        "name": "account",
        "type": "address"
      }
    ],
    "name": "Paused",
    "type": "event"
  },
  {
    "anonymous": false,
    "inputs": [
      {
        "indexed": false,
        "internalType": "uint256",
        "name": "newFeePercent",
        "type": "uint256"
      }
    ],
    "name": "PlatformFeeUpdated",
    "type": "event"
  },
  {
    "anonymous": false,
    "inputs": [
      {
        "indexed": true,
        "internalType": "address",
        "name": "player",
        "type": "address"
      },
      {
        "indexed": false,
        "internalType": "string",
        "name": "username",
        "type": "string"
      }
    ],
    "name": "PlayerRegistered",
    "type": "event"
  },
  {
    "anonymous": false,
    "inputs": [
      {
        "indexed": false,
        "internalType": "uint256",
        "name": "newTimeout",
        "type": "uint256"
      }
    ],
    "name": "TimeoutUpdated",
    "type": "event"
  },
  {
    "anonymous": false,
    "inputs": [
      {
        "indexed": true,
        "internalType": "address",
        "name": "token",
        "type": "address"
      },
      {
        "indexed": false,
        "internalType": "bool",
        "name": "supported",
        "type": "bool"
      }
    ],
    "name": "TokenSupported",
    "type": "event"
  },
  {
    "anonymous": false,
    "inputs": [
      {
        "indexed": false,
        "internalType": "address",
        "name": "account",
        "type": "address"
      }
    ],
    "name": "Unpaused",
    "type": "event"
  },
  {
    "inputs": [],
    "name": "LEADERBOARD_SIZE",
    "outputs": [
      {
        "internalType": "uint256",
        "name": "",
        "type": "uint256"
      }
    ],
    "stateMutability": "view",
    "type": "function"
  },
  {
    "inputs": [],
    "name": "MAX_WIN_RECORDS",
    "outputs": [
      {
        "internalType": "uint256",
        "name": "",
        "type": "uint256"
      }
    ],
    "stateMutability": "view",
    "type": "function"
  },
  {
    "inputs": [
      {
        "internalType": "uint256",
        "name": "challengeId",
        "type": "uint256"
      },
      {
        "internalType": "uint8",
        "name": "moveIndex",
        "type": "uint8"
      }
    ],
    "name": "acceptChallenge",
    "outputs": [],
    "stateMutability": "payable",
    "type": "function"
  },
  {
    "inputs": [
      {
        "internalType": "address",
        "name": "admin",
        "type": "address"
      }
    ],
    "name": "addAdmin",
    "outputs": [],
    "stateMutability": "nonpayable",
    "type": "function"
  },
  {
    "inputs": [
      {
        "internalType": "address",
        "name": "",
        "type": "address"
      }
    ],
    "name": "admins",
    "outputs": [
      {
        "internalType": "bool",
        "name": "",
        "type": "bool"
      }
    ],
    "stateMutability": "view",
    "type": "function"
  },
  {
    "inputs": [],
    "name": "challengeCounter",
    "outputs": [
      {
        "internalType": "uint256",
        "name": "",
        "type": "uint256"
      }
    ],
    "stateMutability": "view",
    "type": "function"
  },
  {
    "inputs": [
      {
        "internalType": "uint256",
        "name": "",
        "type": "uint256"
      }
    ],
    "name": "challenges",
    "outputs": [
      {
        "internalType": "address",
        "name": "challenger",
        "type": "address"
      },
      {
        "internalType": "string",
        "name": "challengerUsername",
        "type": "string"
      },
      {
        "internalType": "address",
        "name": "challenged",
        "type": "address"
      },
      {
        "internalType": "string",
        "name": "challengedUsername",
        "type": "string"
      },
      {
        "internalType": "uint256",
        "name": "betAmount",
        "type": "uint256"
      },
      {
        "internalType": "address",
        "name": "tokenAddress",
        "type": "address"
      },
      {
        "internalType": "uint256",
        "name": "timestamp",
        "type": "uint256"
      },
      {
        "internalType": "bool",
        "name": "accepted",
        "type": "bool"
      },
      {
        "internalType": "uint256",
        "name": "gameId",
        "type": "uint256"
      }
    ],
    "stateMutability": "view",
    "type": "function"
  },
  {
    "inputs": [
      {
        "internalType": "address",
        "name": "challenged",
        "type": "address"
      },
      {
        "internalType": "uint256",
        "name": "betAmount",
        "type": "uint256"
      },
      {
        "internalType": "address",
        "name": "tokenAddress",
        "type": "address"
      }
    ],
    "name": "createChallenge",
    "outputs": [],
    "stateMutability": "payable",
    "type": "function"
  },
  {
    "inputs": [
      {
        "internalType": "uint256",
        "name": "betAmount",
        "type": "uint256"
      },
      {
        "internalType": "uint8",
        "name": "moveIndex",
        "type": "uint8"
      },
      {
        "internalType": "address",
        "name": "tokenAddress",
        "type": "address"
      }
    ],
    "name": "createGame",
    "outputs": [],
    "stateMutability": "payable",
    "type": "function"
  },
  {
    "inputs": [
      {
        "internalType": "uint256",
        "name": "gameId",
        "type": "uint256"
      }
    ],
    "name": "forfeitGame",
    "outputs": [],
    "stateMutability": "nonpayable",
    "type": "function"
  },
  {
    "inputs": [
      {
        "internalType": "uint256",
        "name": "",
        "type": "uint256"
      }
    ],
    "name": "games",
    "outputs": [
      {
        "internalType": "address",
        "name": "playerOne",
        "type": "address"
      },
      {
        "internalType": "address",
        "name": "playerTwo",
        "type": "address"
      },
      {
        "internalType": "uint256",
        "name": "betAmount",
        "type": "uint256"
      },
      {
        "internalType": "address",
        "name": "tokenAddress",
        "type": "address"
      },
      {
        "internalType": "bool",
        "name": "isPlayerOneTurn",
        "type": "bool"
      },
      {
        "internalType": "address",
        "name": "winner",
        "type": "address"
      },
      {
        "internalType": "uint64",
        "name": "lastMoveTimestamp",
        "type": "uint64"
      },
      {
        "internalType": "enum BlOcXTacToe.GameStatus",
        "name": "status",
        "type": "uint8"
      }
    ],
    "stateMutability": "view",
    "type": "function"
  },
  {
    "inputs": [
      {
        "internalType": "uint256",
        "name": "challengeId",
        "type": "uint256"
      }
    ],
    "name": "getChallenge",
    "outputs": [
      {
        "components": [
          {
            "internalType": "address",
            "name": "challenger",
            "type": "address"
          },
          {
            "internalType": "string",
            "name": "challengerUsername",
            "type": "string"
          },
          {
            "internalType": "address",
            "name": "challenged",
            "type": "address"
          },
          {
            "internalType": "string",
            "name": "challengedUsername",
            "type": "string"
          },
          {
            "internalType": "uint256",
            "name": "betAmount",
            "type": "uint256"
          },
          {
            "internalType": "address",
            "name": "tokenAddress",
            "type": "address"
          },
          {
            "internalType": "uint256",
            "name": "timestamp",
            "type": "uint256"
          },
          {
            "internalType": "bool",
            "name": "accepted",
            "type": "bool"
          },
          {
            "internalType": "uint256",
            "name": "gameId",
            "type": "uint256"
          }
        ],
        "internalType": "struct BlOcXTacToe.Challenge",
        "name": "",
        "type": "tuple"
      }
    ],
    "stateMutability": "view",
    "type": "function"
  },
  {
    "inputs": [
      {
        "internalType": "uint256",
        "name": "gameId",
        "type": "uint256"
      }
    ],
    "name": "getGame",
    "outputs": [
      {
        "components": [
          {
            "internalType": "address",
            "name": "playerOne",
            "type": "address"
          },
          {
            "internalType": "address",
            "name": "playerTwo",
            "type": "address"
          },
          {
            "internalType": "uint256",
            "name": "betAmount",
            "type": "uint256"
          },
          {
            "internalType": "address",
            "name": "tokenAddress",
            "type": "address"
          },
          {
            "internalType": "uint8[9]",
            "name": "board",
            "type": "uint8[9]"
          },
          {
            "internalType": "bool",
            "name": "isPlayerOneTurn",
            "type": "bool"
          },
          {
            "internalType": "address",
            "name": "winner",
            "type": "address"
          },
          {
            "internalType": "uint64",
            "name": "lastMoveTimestamp",
            "type": "uint64"
          },
          {
            "internalType": "enum BlOcXTacToe.GameStatus",
            "name": "status",
            "type": "uint8"
          }
        ],
        "internalType": "struct BlOcXTacToe.Game",
        "name": "",
        "type": "tuple"
      }
    ],
    "stateMutability": "view",
    "type": "function"
  },
  {
    "inputs": [],
    "name": "getLatestGameId",
    "outputs": [
      {
        "internalType": "uint256",
        "name": "",
        "type": "uint256"
      }
    ],
    "stateMutability": "view",
    "type": "function"
  },
  {
    "inputs": [
      {
        "internalType": "uint256",
        "name": "limit",
        "type": "uint256"
      }
    ],
    "name": "getLatestWins",
    "outputs": [
      {
        "components": [
          {
            "internalType": "uint256",
            "name": "gameId",
            "type": "uint256"
          },
          {
            "internalType": "address",
            "name": "winner",
            "type": "address"
          },
          {
            "internalType": "string",
            "name": "winnerUsername",
            "type": "string"
          },
          {
            "internalType": "address",
            "name": "opponent",
            "type": "address"
          },
          {
            "internalType": "string",
            "name": "opponentUsername",
            "type": "string"
          },
          {
            "internalType": "uint256",
            "name": "payout",
            "type": "uint256"
          },
          {
            "internalType": "uint256",
            "name": "timestamp",
            "type": "uint256"
          }
        ],
        "internalType": "struct BlOcXTacToe.WinRecord[]",
        "name": "",
        "type": "tuple[]"
      }
    ],
    "stateMutability": "view",
    "type": "function"
  },
  {
    "inputs": [
      {
        "internalType": "uint256",
        "name": "limit",
        "type": "uint256"
      }
    ],
    "name": "getLeaderboard",
    "outputs": [
      {
        "components": [
          {
            "internalType": "address",
            "name": "player",
            "type": "address"
          },
          {
            "internalType": "string",
            "name": "username",
            "type": "string"
          },
          {
            "internalType": "uint256",
            "name": "rating",
            "type": "uint256"
          },
          {
            "internalType": "uint256",
            "name": "wins",
            "type": "uint256"
          }
        ],
        "internalType": "struct BlOcXTacToe.LeaderboardEntry[]",
        "name": "",
        "type": "tuple[]"
      }
    ],
    "stateMutability": "view",
    "type": "function"
  },
  {
    "inputs": [
      {
        "internalType": "address",
        "name": "player",
        "type": "address"
      }
    ],
    "name": "getPlayer",
    "outputs": [
      {
        "components": [
          {
            "internalType": "string",
            "name": "username",
            "type": "string"
          },
          {
            "internalType": "uint256",
            "name": "wins",
            "type": "uint256"
          },
          {
            "internalType": "uint256",
            "name": "losses",
            "type": "uint256"
          },
          {
            "internalType": "uint256",
            "name": "draws",
            "type": "uint256"
          },
          {
            "internalType": "uint256",
            "name": "totalGames",
            "type": "uint256"
          },
          {
            "internalType": "uint256",
            "name": "rating",
            "type": "uint256"
          },
          {
            "internalType": "bool",
            "name": "registered",
            "type": "bool"
          }
        ],
        "internalType": "struct BlOcXTacToe.Player",
        "name": "",
        "type": "tuple"
      }
    ],
    "stateMutability": "view",
    "type": "function"
  },
  {
    "inputs": [
      {
        "internalType": "string",
        "name": "username",
        "type": "string"
      }
    ],
    "name": "getPlayerByUsername",
    "outputs": [
      {
        "internalType": "address",
        "name": "",
        "type": "address"
      },
      {
        "components": [
          {
            "internalType": "string",
            "name": "username",
            "type": "string"
          },
          {
            "internalType": "uint256",
            "name": "wins",
            "type": "uint256"
          },
          {
            "internalType": "uint256",
            "name": "losses",
            "type": "uint256"
          },
          {
            "internalType": "uint256",
            "name": "draws",
            "type": "uint256"
          },
          {
            "internalType": "uint256",
            "name": "totalGames",
            "type": "uint256"
          },
          {
            "internalType": "uint256",
            "name": "rating",
            "type": "uint256"
          },
          {
            "internalType": "bool",
            "name": "registered",
            "type": "bool"
          }
        ],
        "internalType": "struct BlOcXTacToe.Player",
        "name": "",
        "type": "tuple"
      }
    ],
    "stateMutability": "view",
    "type": "function"
  },
  {
    "inputs": [
      {
        "internalType": "address",
        "name": "player",
        "type": "address"
      }
    ],
    "name": "getPlayerChallenges",
    "outputs": [
      {
        "internalType": "uint256[]",
        "name": "",
        "type": "uint256[]"
      }
    ],
    "stateMutability": "view",
    "type": "function"
  },
  {
    "inputs": [],
    "name": "getSupportedTokens",
    "outputs": [
      {
        "internalType": "address[]",
        "name": "",
        "type": "address[]"
      }
    ],
    "stateMutability": "view",
    "type": "function"
  },
  {
    "inputs": [
      {
        "internalType": "uint256",
        "name": "gameId",
        "type": "uint256"
      }
    ],
    "name": "getTimeRemaining",
    "outputs": [
      {
        "internalType": "uint256",
        "name": "",
        "type": "uint256"
      }
    ],
    "stateMutability": "view",
    "type": "function"
  },
  {
    "inputs": [
      {
        "internalType": "address",
        "name": "token",
        "type": "address"
      }
    ],
    "name": "isTokenSupported",
    "outputs": [
      {
        "internalType": "bool",
        "name": "",
        "type": "bool"
      }
    ],
    "stateMutability": "view",
    "type": "function"
  },
  {
    "inputs": [
      {
        "internalType": "uint256",
        "name": "gameId",
        "type": "uint256"
      },
      {
        "internalType": "uint8",
        "name": "moveIndex",
        "type": "uint8"
      }
    ],
    "name": "joinGame",
    "outputs": [],
    "stateMutability": "payable",
    "type": "function"
  },
  {
    "inputs": [
      {
        "internalType": "uint256",
        "name": "",
        "type": "uint256"
      }
    ],
    "name": "latestWins",
    "outputs": [
      {
        "internalType": "uint256",
        "name": "gameId",
        "type": "uint256"
      },
      {
        "internalType": "address",
        "name": "winner",
        "type": "address"
      },
      {
        "internalType": "string",
        "name": "winnerUsername",
        "type": "string"
      },
      {
        "internalType": "address",
        "name": "opponent",
        "type": "address"
      },
      {
        "internalType": "string",
        "name": "opponentUsername",
        "type": "string"
      },
      {
        "internalType": "uint256",
        "name": "payout",
        "type": "uint256"
      },
      {
        "internalType": "uint256",
        "name": "timestamp",
        "type": "uint256"
      }
    ],
    "stateMutability": "view",
    "type": "function"
  },
  {
    "inputs": [
      {
        "internalType": "uint256",
        "name": "",
        "type": "uint256"
      }
    ],
    "name": "leaderboard",
    "outputs": [
      {
        "internalType": "address",
        "name": "player",
        "type": "address"
      },
      {
        "internalType": "string",
        "name": "username",
        "type": "string"
      },
      {
        "internalType": "uint256",
        "name": "rating",
        "type": "uint256"
      },
      {
        "internalType": "uint256",
        "name": "wins",
        "type": "uint256"
      }
    ],
    "stateMutability": "view",
    "type": "function"
  },
  {
    "inputs": [],
    "name": "moveTimeout",
    "outputs": [
      {
        "internalType": "uint256",
        "name": "",
        "type": "uint256"
      }
    ],
    "stateMutability": "view",
    "type": "function"
  },
  {
    "inputs": [],
    "name": "owner",
    "outputs": [
      {
        "internalType": "address",
        "name": "",
        "type": "address"
      }
    ],
    "stateMutability": "view",
    "type": "function"
  },
  {
    "inputs": [],
    "name": "pause",
    "outputs": [],
    "stateMutability": "nonpayable",
    "type": "function"
  },
  {
    "inputs": [],
    "name": "paused",
    "outputs": [
      {
        "internalType": "bool",
        "name": "",
        "type": "bool"
      }
    ],
    "stateMutability": "view",
    "type": "function"
  },
  {
    "inputs": [],
    "name": "platformFeePercent",
    "outputs": [
      {
        "internalType": "uint256",
        "name": "",
        "type": "uint256"
      }
    ],
    "stateMutability": "view",
    "type": "function"
  },
  {
    "inputs": [],
    "name": "platformFeeRecipient",
    "outputs": [
      {
        "internalType": "address",
        "name": "",
        "type": "address"
      }
    ],
    "stateMutability": "view",
    "type": "function"
  },
  {
    "inputs": [
      {
        "internalType": "uint256",
        "name": "gameId",
        "type": "uint256"
      },
      {
        "internalType": "uint8",
        "name": "moveIndex",
        "type": "uint8"
      }
    ],
    "name": "play",
    "outputs": [],
    "stateMutability": "nonpayable",
    "type": "function"
  },
  {
    "inputs": [
      {
        "internalType": "address",
        "name": "",
        "type": "address"
      },
      {
        "internalType": "uint256",
        "name": "",
        "type": "uint256"
      }
    ],
    "name": "playerChallenges",
    "outputs": [
      {
        "internalType": "uint256",
        "name": "",
        "type": "uint256"
      }
    ],
    "stateMutability": "view",
    "type": "function"
  },
  {
    "inputs": [
      {
        "internalType": "address",
        "name": "",
        "type": "address"
      }
    ],
    "name": "players",
    "outputs": [
      {
        "internalType": "string",
        "name": "username",
        "type": "string"
      },
      {
        "internalType": "uint256",
        "name": "wins",
        "type": "uint256"
      },
      {
        "internalType": "uint256",
        "name": "losses",
        "type": "uint256"
      },
      {
        "internalType": "uint256",
        "name": "draws",
        "type": "uint256"
      },
      {
        "internalType": "uint256",
        "name": "totalGames",
        "type": "uint256"
      },
      {
        "internalType": "uint256",
        "name": "rating",
        "type": "uint256"
      },
      {
        "internalType": "bool",
        "name": "registered",
        "type": "bool"
      }
    ],
    "stateMutability": "view",
    "type": "function"
  },
  {
    "inputs": [
      {
        "internalType": "string",
        "name": "username",
        "type": "string"
      }
    ],
    "name": "registerPlayer",
    "outputs": [],
    "stateMutability": "nonpayable",
    "type": "function"
  },
  {
    "inputs": [
      {
        "internalType": "uint256",
        "name": "",
        "type": "uint256"
      }
    ],
    "name": "registeredPlayers",
    "outputs": [
      {
        "internalType": "address",
        "name": "",
        "type": "address"
      }
    ],
    "stateMutability": "view",
    "type": "function"
  },
  {
    "inputs": [
      {
        "internalType": "address",
        "name": "admin",
        "type": "address"
      }
    ],
    "name": "removeAdmin",
    "outputs": [],
    "stateMutability": "nonpayable",
    "type": "function"
  },
  {
    "inputs": [],
    "name": "renounceOwnership",
    "outputs": [],
    "stateMutability": "nonpayable",
    "type": "function"
  },
  {
    "inputs": [
      {
        "internalType": "uint256",
        "name": "newTimeout",
        "type": "uint256"
      }
    ],
    "name": "setMoveTimeout",
    "outputs": [],
    "stateMutability": "nonpayable",
    "type": "function"
  },
  {
    "inputs": [
      {
        "internalType": "uint256",
        "name": "newFeePercent",
        "type": "uint256"
      }
    ],
    "name": "setPlatformFee",
    "outputs": [],
    "stateMutability": "nonpayable",
    "type": "function"
  },
  {
    "inputs": [
      {
        "internalType": "address",
        "name": "recipient",
        "type": "address"
      }
    ],
    "name": "setPlatformFeeRecipient",
    "outputs": [],
    "stateMutability": "nonpayable",
    "type": "function"
  },
  {
    "inputs": [
      {
        "internalType": "address",
        "name": "token",
        "type": "address"
      },
      {
        "internalType": "bool",
        "name": "supported",
        "type": "bool"
      }
    ],
    "name": "setSupportedToken",
    "outputs": [],
    "stateMutability": "nonpayable",
    "type": "function"
  },
  {
    "inputs": [
      {
        "internalType": "address",
        "name": "",
        "type": "address"
      }
    ],
    "name": "supportedTokens",
    "outputs": [
      {
        "internalType": "bool",
        "name": "",
        "type": "bool"
      }
    ],
    "stateMutability": "view",
    "type": "function"
  },
  {
    "inputs": [
      {
        "internalType": "uint256",
        "name": "",
        "type": "uint256"
      }
    ],
    "name": "supportedTokensList",
    "outputs": [
      {
        "internalType": "address",
        "name": "",
        "type": "address"
      }
    ],
    "stateMutability": "view",
    "type": "function"
  },
  {
    "inputs": [
      {
        "internalType": "address",
        "name": "newOwner",
        "type": "address"
      }
    ],
    "name": "transferOwnership",
    "outputs": [],
    "stateMutability": "nonpayable",
    "type": "function"
  },
  {
    "inputs": [],
    "name": "unpause",
    "outputs": [],
    "stateMutability": "nonpayable",
    "type": "function"
  },
  {
    "inputs": [
      {
        "internalType": "string",
        "name": "",
        "type": "string"
      }
    ],
    "name": "usernameToAddress",
    "outputs": [
      {
        "internalType": "address",
        "name": "",
        "type": "address"
      }
    ],
    "stateMutability": "view",
    "type": "function"
  }
]
